uainepydat/bitgen.py
uainepydat/blobhelper.py
uainepydat/dataclean.py
uainepydat/datagen.py
uainepydat/datahash.py
uainepydat/dataio.py
uainepydat/datatransform.py
uainepydat/duckfunc.py
uainepydat/fileio.py
uainepydat/frameverifier.py
uainepydat/systeminfo.py
uainepydat-1.6.3.dist-info/LICENSE
uainepydat-1.6.3.dist-info/METADATA
uainepydat-1.6.3.dist-info/WHEEL
uainepydat-1.6.3.dist-info/top_level.txt
uainepydat-1.6.3.dist-info/RECORD
