Metadata-Version: 2.1
Name: uainepydat
Version: 1.6.3
Summary: A python package to assist in data and database handling
Home-page: https://github.com/uaineteine/uaine.pydat
Author: Daniel Stamer-Squair
Author-email: uaine.teine@hotmail.com
Classifier: Programming Language :: Python :: 3
Classifier: License :: OSI Approved :: GNU General Public License v3 (GPLv3)
Classifier: Operating System :: OS Independent
Requires-Python: >=3.9
License-File: LICENSE
Requires-Dist: pandas
Requires-Dist: pyreadstat <=1.3.0,>=1.2.8
Requires-Dist: requests
Requires-Dist: duckdb
Requires-Dist: wheel
Requires-Dist: twine
Requires-Dist: psutil
Requires-Dist: lxml
Requires-Dist: polars
Requires-Dist: azure-storage-blob
Requires-Dist: tqdm
Requires-Dist: pyarrow
